xmkckks/__init__.py
xmkckks/rlwe.py
xmkckks/rq.py
xmkckks/utils.py
xmkckks-0.0.2.dist-info/METADATA
xmkckks-0.0.2.dist-info/WHEEL
xmkckks-0.0.2.dist-info/top_level.txt
xmkckks-0.0.2.dist-info/RECORD
