Metadata-Version: 2.4
Name: xmkckks
Version: 0.0.2
Summary: A package for xmkckks
Author-email: mmRoshani <mohammadmojtabaroshani@outlook.com>
License: MIT
Project-URL: Homepage, https://github.com/mmRoshani/xmkckks
Requires-Python: >=3.12
Requires-Dist: numpy>=1.24
